{"id": "515661f6-59c8-41e4-b05d-ca0ecc43ce95", "text": "the orthogonal projection of bonto the subspace spanned by the columns\nof A. This problem arises often in practice, and the solution is called the\nleast-squares solution (assuming the dot product as the inner product) ofleast-squares\nsolution an overdetermined system. This is discussed further in Section 9.4. Using\nreconstruction errors (3.63) is one possible approach to derive principal\ncomponent analysis (Section 10.3).\nRemark. We just looked at projections of vectorsxonto a subspaceU with", "metadata": {"producer": "pdfTeX-1.40.20", "creator": "LaTeX with hyperref", "creationdate": "2019-10-15T12:48:02+01:00", "author": "Marc Peter Deisenroth, A. Aldo Faisal, Cheng Soon Ong", "keywords": "", "moddate": "2020-01-03T10:00:34+02:00", "ptex.fullbanner": "This is pdfTeX, Version 3.14159265-2.6-1.40.20 (TeX Live 2019) kpathsea version 6.3.1", "subject": "", "title": "Mathematics for Machine Learning", "trapped": "/False", "source": "/home/haas/rag_proj/samples/AAPMOR Website/Mathematics for Machine Learning ( etc.) (Z-Library).pdf", "total_pages": 417, "page": 93, "page_label": "88"}}