{"id": "c535a76d-382c-4a01-89b1-c955be3abd1e", "text": "ma lrix R is aJ .. 'tlyt Ih~ ~mt. The original A romp/nely dntrmints 1M I \",14 l' 11114 \n~,ro m .. 's in R. \",,<,OIding '0 le: \nThe pivOi wlumns Of? no/ combinations of earlier column! of A. \nThe free columns Ort combinalions of earlier columns (1' tells the combina tions).", "metadata": {"producer": "Adobe Acrobat 9.0 Paper Capture Plug-in", "creator": "PyPDF", "creationdate": "2010-03-03T12:24:37+00:00", "author": "", "moddate": "2010-05-26T00:47:43-03:00", "source": "/home/haas/rag_proj/samples/AAPMOR Website/Introduction to Linear Algebra, 3rd edition (Gilbert Strang) (Z-Library).pdf", "total_pages": 578, "page": 146, "page_label": "147"}}