{"id": "bb734bfe-77cf-4466-827c-791b60c6c483", "text": "10 (Suggested by C. Van Loan.) Find the L U faclonZlllion of A = [r: J. On your \ncom puter !!Olve by eliminatiOll when ~ = IO- J .IO-6.1O-9.1O- 1~. IO- I ): \nThe true ~ is (I. I). Mak e a table to show the error for each~. Exchange the \ntwo equations and sol\"e again-the CmIfll should almost disappear. \n11 Choose sinO and cosll to triangularize A. and find R : \nA = [ ~' - \"~ \" 'll ' -'lor· ·l=N. O tl sinll rose 3 ~ O. \n12 Choose sinO and cosO to make Q lIAQ 1tl triangular (same A). W hat a~ the", "metadata": {"producer": "Adobe Acrobat 9.0 Paper Capture Plug-in", "creator": "PyPDF", "creationdate": "2010-03-03T12:24:37+00:00", "author": "", "moddate": "2010-05-26T00:47:43-03:00", "source": "/home/haas/rag_proj/samples/AAPMOR Website/Introduction to Linear Algebra, 3rd edition (Gilbert Strang) (Z-Library).pdf", "total_pages": 578, "page": 466, "page_label": "467"}}