{"id": "7f65a4a3-2702-42f0-be97-47b0e933dafa", "text": "S.l Cr.\"\",,', Mule. I ............ \"\"\" ~umes 25 9 \n36 1lH: sym~ric !'aKal malrices llave determinant L. If I subtract I from the n. n \nenlly. why doe~ lhe delerminant become zero? (Use rule 3 or cofactim in row \n,., \n~, [! \n, , \n~ 1 = , (koo.\" ~, [! \n, I \n~ 1 = 0 (10 \"pI,;\". 2 J 2 3 \nJ , J , , 10 , 10 19 \nCRAMER'S RULE , INVERSES , AND VOLUMES. 5.3 \nThis section applies delerminants 10 sol'\" A .r = b and also to in'~n A . In tile en lri e~", "metadata": {"producer": "Adobe Acrobat 9.0 Paper Capture Plug-in", "creator": "PyPDF", "creationdate": "2010-03-03T12:24:37+00:00", "author": "", "moddate": "2010-05-26T00:47:43-03:00", "source": "/home/haas/rag_proj/samples/AAPMOR Website/Introduction to Linear Algebra, 3rd edition (Gilbert Strang) (Z-Library).pdf", "total_pages": 578, "page": 267, "page_label": "268"}}