{"id": "69e4cbe1-9efd-4501-abff-f91ffce4f88e", "text": "same statement for functioos. W e can raise or lower /(,,) by the same amount C. \nwithoul changing its deri\\lllti\",. \"There is an arbitlll'Y con~tant C in the integral. \n,", "metadata": {"producer": "Adobe Acrobat 9.0 Paper Capture Plug-in", "creator": "PyPDF", "creationdate": "2010-03-03T12:24:37+00:00", "author": "", "moddate": "2010-05-26T00:47:43-03:00", "source": "/home/haas/rag_proj/samples/AAPMOR Website/Introduction to Linear Algebra, 3rd edition (Gilbert Strang) (Z-Library).pdf", "total_pages": 578, "page": 423, "page_label": "424"}}