{"id": "6ed3e61f-1455-437e-a6f2-5501814939cc", "text": "I. A transfOl\"TTWion T ur. k~s e\"\"h ~ in the input space to T(,) in t~ output space. \n2. Linearity requires that T (ctgl + ... + c.g.) = ct T (pLl + ... +c. T ( •• ). \nJ. The transformation T (.) = A , + '0 is linear only if ~O = 0 ! \n4. The quilt on the book cover shows T(house) '\" All fQr nine nwrke s A. \n, \nt", "metadata": {"producer": "Adobe Acrobat 9.0 Paper Capture Plug-in", "creator": "PyPDF", "creationdate": "2010-03-03T12:24:37+00:00", "author": "", "moddate": "2010-05-26T00:47:43-03:00", "source": "/home/haas/rag_proj/samples/AAPMOR Website/Introduction to Linear Algebra, 3rd edition (Gilbert Strang) (Z-Library).pdf", "total_pages": 578, "page": 373, "page_label": "374"}}