{"id": "5125d41d-4480-4e47-83a2-742c2fbd2ca1", "text": "8.5 Fouri .... Sefi ... : Linear Algebra 10< Functions 4 37 \nFOURIER SERIES: LINEAR ALGEBRA FOR FUNCTIONS. 8.5 \nThis section goes from finite dimensions to infinite dimensions. I want to explain linear \nalgebra in infinite-dimensional space. and to show that it still works. First step: look \nback. This book began with vectors and dot products and linear combinations. We \nbegin by conveniog those basic ideas to the infinite case-then the rest will follow.", "metadata": {"producer": "Adobe Acrobat 9.0 Paper Capture Plug-in", "creator": "PyPDF", "creationdate": "2010-03-03T12:24:37+00:00", "author": "", "moddate": "2010-05-26T00:47:43-03:00", "source": "/home/haas/rag_proj/samples/AAPMOR Website/Introduction to Linear Algebra, 3rd edition (Gilbert Strang) (Z-Library).pdf", "total_pages": 578, "page": 445, "page_label": "446"}}