{"id": "f210b5c4-56ef-4e1b-8884-9bc0c900e0eb", "text": "Reason: If \"'e pick II. b. or d from column 3, that column is u~ up. Then the only \navailable choice from row 3 is zero. \nHc~ is a diffe~nt reason for the same answer. If c '\" O. lhen Z has a row of \nzeros and del Z '\" c '\" 0 is COtTt'CL If c is not zero. uSt tlimirllliion. Subtract multipks \nof row J from the other rows, to knock QUI l1.b,d. llLa.t kaves a diagonal matrix and \ndctZ \",c. \nThis example will SOO1t be u~ for \"elllmers Rule\", If we move 11, b, c, d inlO", "metadata": {"producer": "Adobe Acrobat 9.0 Paper Capture Plug-in", "creator": "PyPDF", "creationdate": "2010-03-03T12:24:37+00:00", "author": "", "moddate": "2010-05-26T00:47:43-03:00", "source": "/home/haas/rag_proj/samples/AAPMOR Website/Introduction to Linear Algebra, 3rd edition (Gilbert Strang) (Z-Library).pdf", "total_pages": 578, "page": 257, "page_label": "258"}}