{"id": "40cd1b59-cfc1-438b-a036-50add6eb2b4b", "text": "12.5. Case Study 3: Seasonality 219\n12.5 Case Study 3: Seasonality\nThe monthly mean temperatures dataset summarizes the monthly average air temperatures in\nNottingham Castle, England from 1920 to 1939 in degrees Fahrenheit. For more information on\nthis dataset, see Chapter 11 where it was introduced. You can download the dataset directly\nfrom here:\n monthly-mean-temp.csv 3\nSave the ﬁle with the ﬁlename monthly-mean-temp.csv in your current working directory.", "metadata": {"producer": "pdfTeX-1.40.18", "creator": "LaTeX with hyperref package", "creationdate": "2018-11-01T07:53:25+11:00", "author": "", "title": "", "subject": "", "keywords": "", "moddate": "2018-11-01T07:53:25+11:00", "trapped": "/False", "ptex.fullbanner": "This is pdfTeX, Version 3.14159265-2.6-1.40.18 (TeX Live 2017) kpathsea version 6.2.3", "source": "/home/haas/rag_proj/samples/AAPMOR Website/Deep Learning for Time Series Forecasting - Predict the Future with MLPs, CNNs and LSTMs in Python (Jason Brownlee) (Z-Library).pdf", "total_pages": 574, "page": 235, "page_label": "219"}}