{"id": "3daa3ea7-4449-4d2b-9dac-61cf60c5c82e", "text": "R jusl picks oot the first r columns of E - 1. \nOne more facl about piVQt columns. nv\"ir definitioo has becn purely computa · \ntional. based on R. H ere is a direct mathematical descriplion of the piVQt columns of A : \nJC T\"~ pi..\" CQlu mn s II\"\" n()/ combina/,'onl of hlrliu w/umnl . Tbe f\"\", column. \n\",... combtnauOfIs of earlier colutnn\\. l1tc<.e combinalion; are the specIal '\\OIUlions! \nA pivot column of R (wilh I in the piVQt row) cannot be a combination of ear­", "metadata": {"producer": "Adobe Acrobat 9.0 Paper Capture Plug-in", "creator": "PyPDF", "creationdate": "2010-03-03T12:24:37+00:00", "author": "", "moddate": "2010-05-26T00:47:43-03:00", "source": "/home/haas/rag_proj/samples/AAPMOR Website/Introduction to Linear Algebra, 3rd edition (Gilbert Strang) (Z-Library).pdf", "total_pages": 578, "page": 144, "page_label": "145"}}