{"id": "ad87aeb3-5d3f-4f95-ba70-a4300832c47e", "text": "40 unainly tiT ;s nonhwe>t . 8 l i • • full matrix! 8 - 1 is _the ... : [ : ~ rl '\" [ ~ _: J. \n\"The rowS of 8 ~ in ~\"\" onle. from I )00, .... triangular L • .., 8 = PC n..n 8 - 1 .. \nL - Ip - I has tho ro/\"\"\"\" in re\" ..... order from L- I. So 8 - t ;. _,~,. NorUIwe<I \ntimes ..,..the ... i, uJ'PC1\" ,riangular! 8 .. PI. and C .. PU give 8C .. (pLP )U _ \"J'PC1\" \ntime. uJ'PC1\". \n41 The i. j ~ntry of PA l' i, the .. - I + I.\" - J + I ~n'ry of A . 'The moin dilgonal rcverKS orde-r.", "metadata": {"producer": "Adobe Acrobat 9.0 Paper Capture Plug-in", "creator": "PyPDF", "creationdate": "2010-03-03T12:24:37+00:00", "author": "", "moddate": "2010-05-26T00:47:43-03:00", "source": "/home/haas/rag_proj/samples/AAPMOR Website/Introduction to Linear Algebra, 3rd edition (Gilbert Strang) (Z-Library).pdf", "total_pages": 578, "page": 520, "page_label": "521"}}