{"id": "5cfe8b46-4b9f-4efc-89fc-7d816c272994", "text": "that y= Axis a transformed version of x. We can compute the mean of\nyby exploiting that the expectation is a linear operator (6.50) as follows:\nE[y] = E[Ax] = AE[x] = Aµ. (6.86)\nSimilarly the variance of ycan be found by using (6.51):\nV[y] = V[Ax] = AV[x]A⊤= AΣA⊤. (6.87)\nThis means that the random variable yis distributed according to\np(y) = N\n(\ny|Aµ, AΣA⊤)\n. (6.88)\nc⃝2019 M. P. Deisenroth, A. A. Faisal, C. S. Ong. To be published by Cambridge University Press.", "metadata": {"producer": "pdfTeX-1.40.20", "creator": "LaTeX with hyperref", "creationdate": "2019-10-15T12:48:02+01:00", "author": "Marc Peter Deisenroth, A. Aldo Faisal, Cheng Soon Ong", "keywords": "", "moddate": "2020-01-03T10:00:34+02:00", "ptex.fullbanner": "This is pdfTeX, Version 3.14159265-2.6-1.40.20 (TeX Live 2019) kpathsea version 6.3.1", "subject": "", "title": "Mathematics for Machine Learning", "trapped": "/False", "source": "/home/haas/rag_proj/samples/AAPMOR Website/Mathematics for Machine Learning ( etc.) (Z-Library).pdf", "total_pages": 417, "page": 208, "page_label": "203"}}