{"id": "4892c7c7-2c07-4a74-8dd4-62d3714c2a18", "text": "A Can be diagonalized. In lhe general case. eigen\"ecIOl\"S an: missing and A can'l be \nn:achcd. \nSuppose A has J independent eigenvectors. Then it is similar to a matrix wilh J \nblocks. Each block is like J in Example 3, 7111' rigetlWJ/ue is 011 the diagonal and rhe \ndiagonol aool'e it comain. I·s. This block accounls for one eigen''t'C1Of of A. W ben \nlhen: an: n eigenve<:lors and \" blocks, the~ are all I by I. In lhal case J is A.", "metadata": {"producer": "Adobe Acrobat 9.0 Paper Capture Plug-in", "creator": "PyPDF", "creationdate": "2010-03-03T12:24:37+00:00", "author": "", "moddate": "2010-05-26T00:47:43-03:00", "source": "/home/haas/rag_proj/samples/AAPMOR Website/Introduction to Linear Algebra, 3rd edition (Gilbert Strang) (Z-Library).pdf", "total_pages": 578, "page": 354, "page_label": "355"}}