{"id": "5604eeef-183f-4d92-9244-28bb1864d9b0", "text": "17.4. Model Evaluation 347\nfor i in range(actual.shape[1]):\n# calculate mse\nmse = mean_squared_error(actual[:, i], predicted[:, i])\n# calculate rmse\nrmse = sqrt(mse)\n# store\nscores.append(rmse)\n# calculate overall RMSE\ns = 0\nfor row in range(actual.shape[0]):\nfor col in range(actual.shape[1]):\ns += (actual[row, col] - predicted[row, col])**2\nscore = sqrt(s / (actual.shape[0] * actual.shape[1]))\nreturn score, scores\nListing 17.9: Example of a function for evaluating forecasts.", "metadata": {"producer": "pdfTeX-1.40.18", "creator": "LaTeX with hyperref package", "creationdate": "2018-11-01T07:53:25+11:00", "author": "", "title": "", "subject": "", "keywords": "", "moddate": "2018-11-01T07:53:25+11:00", "trapped": "/False", "ptex.fullbanner": "This is pdfTeX, Version 3.14159265-2.6-1.40.18 (TeX Live 2017) kpathsea version 6.2.3", "source": "/home/haas/rag_proj/samples/AAPMOR Website/Deep Learning for Time Series Forecasting - Predict the Future with MLPs, CNNs and LSTMs in Python (Jason Brownlee) (Z-Library).pdf", "total_pages": 574, "page": 363, "page_label": "347"}}