{"id": "dba2aec0-312c-4c5a-a90a-bde7d4cb0351", "text": "19.6. Univariate CNN Model 372\nInput, Output\n[d01, d02, d03, d04, d05, d06, d07], [d08, d09, d10, d11, d12, d13, d14]\n[d02, d03, d04, d05, d06, d07, d08], [d09, d10, d11, d12, d13, d14, d15]\n...\nListing 19.5: Example of overlapping weekly data.\nWe can do this by keeping track of start and end indexes for the inputs and outputs as we\niterate across the length of the ﬂattened data in terms of time steps. We can also do this in a", "metadata": {"producer": "pdfTeX-1.40.18", "creator": "LaTeX with hyperref package", "creationdate": "2018-11-01T07:53:25+11:00", "author": "", "title": "", "subject": "", "keywords": "", "moddate": "2018-11-01T07:53:25+11:00", "trapped": "/False", "ptex.fullbanner": "This is pdfTeX, Version 3.14159265-2.6-1.40.18 (TeX Live 2017) kpathsea version 6.2.3", "source": "/home/haas/rag_proj/samples/AAPMOR Website/Deep Learning for Time Series Forecasting - Predict the Future with MLPs, CNNs and LSTMs in Python (Jason Brownlee) (Z-Library).pdf", "total_pages": 574, "page": 388, "page_label": "372"}}