{"id": "f166ac72-cf4d-4e89-85ef-c08aeb2e7ad1", "text": "(d) If II is invertible then A' is iIWel'tible. \n30 For which three numlx rs c is this matrix not invm iblc::. and why not? \n[' , '] A =ccc. \no , , \n31 Prove that A is invertible if ,..\"O and,..\" b (find the pivots Of A - t): \n[' , '] A _ a a b . \n, , , \n, \ni", "metadata": {"producer": "Adobe Acrobat 9.0 Paper Capture Plug-in", "creator": "PyPDF", "creationdate": "2010-03-03T12:24:37+00:00", "author": "", "moddate": "2010-05-26T00:47:43-03:00", "source": "/home/haas/rag_proj/samples/AAPMOR Website/Introduction to Linear Algebra, 3rd edition (Gilbert Strang) (Z-Library).pdf", "total_pages": 578, "page": 89, "page_label": "90"}}