{"id": "08dddcd6-dbe1-40d1-9afd-7d041dbc9789", "text": ",l..-.. b h.a. I ool.tion ,.tI<tI ~ -)hI\" 0 and b)-2b 1 .. 0: tile rotum \" spa<:c is til< tine \nlhrough 12.6.41 which i. the inler>e<:lion of the planes bJ -)hI\" 0 and I>J - 2b1 .. 0; lhe \nnullspa<:c C()fII>in, all rombi~ion. of ' l .. (-1/2.1.0) and '2 \" (- 3/2.0.1); particular \nsolution JC p .. d _ (3. O. 0) and romplet<c oolution JC , + rll) + <\":2'2. \n, , \n4 \"- ~ompl~\" - (I'O. !.0)+JCl(-3. ].0 .0)+-<.(0.0. -2. I).", "metadata": {"producer": "Adobe Acrobat 9.0 Paper Capture Plug-in", "creator": "PyPDF", "creationdate": "2010-03-03T12:24:37+00:00", "author": "", "moddate": "2010-05-26T00:47:43-03:00", "source": "/home/haas/rag_proj/samples/AAPMOR Website/Introduction to Linear Algebra, 3rd edition (Gilbert Strang) (Z-Library).pdf", "total_pages": 578, "page": 522, "page_label": "523"}}