{"id": "8be5eb6f-34e7-49eb-89f7-b07235a0c16f", "text": "running the example a few times.\n...\n> 1489.795\n> 1652.620\n> 1537.349\n> 1443.777\n> 1567.179\ncnn: 1524.067 RMSE (+/- 57.148)\nListing 14.33: Example output from a CNN model for forecasting monthly car sales.\nA box and whisker plot of the scores is created to help understand the spread of error across\nthe runs. We can see that the spread does seem to be biased towards larger error values, as we\nwould expect, although the upper whisker of the plot (in this case, the largest error that are not", "metadata": {"producer": "pdfTeX-1.40.18", "creator": "LaTeX with hyperref package", "creationdate": "2018-11-01T07:53:25+11:00", "author": "", "title": "", "subject": "", "keywords": "", "moddate": "2018-11-01T07:53:25+11:00", "trapped": "/False", "ptex.fullbanner": "This is pdfTeX, Version 3.14159265-2.6-1.40.18 (TeX Live 2017) kpathsea version 6.2.3", "source": "/home/haas/rag_proj/samples/AAPMOR Website/Deep Learning for Time Series Forecasting - Predict the Future with MLPs, CNNs and LSTMs in Python (Jason Brownlee) (Z-Library).pdf", "total_pages": 574, "page": 284, "page_label": "268"}}