{"id": "e904a37f-d2c5-4ab0-9cf5-72194fdc71d4", "text": "),6 Oi\"\"\"\"\"\"\" cJ the f\"\", ~.. 177 \nRighi rta.son: l1Ic Ioame combinalions of the columns ~ ~ro. for A and R. Sa~ Ihal \nanofher wa y: Ax = 0 £roclly \"'h~n Rx = O. So the , independenl columns malch. \nConclusWtl l1Ic, piYOl col umn~ of A are a ba~i s for ils column space. \nJ A has the Sllme nullsptWC lIS R . Same dimension n - , and samo:: basis. \nRros(!II: l1Ic elimination steps don'I change Ihe solulioos. l1Ic special solulioos are", "metadata": {"producer": "Adobe Acrobat 9.0 Paper Capture Plug-in", "creator": "PyPDF", "creationdate": "2010-03-03T12:24:37+00:00", "author": "", "moddate": "2010-05-26T00:47:43-03:00", "source": "/home/haas/rag_proj/samples/AAPMOR Website/Introduction to Linear Algebra, 3rd edition (Gilbert Strang) (Z-Library).pdf", "total_pages": 578, "page": 185, "page_label": "186"}}