{"id": "25a9c687-7a4a-47f5-bac6-c1de1ff5b7ca", "text": "Chapter I pmvide s a trier introduction 10 vectors and dot prodllClli. If lhe class \nhas met them before, lhe coorsc Can begin with Chapter 2. 1ba1 chapter sol,-es \nn by n systems Ax : h. and prepa'\"'\" for the whole course. \nI now use lhe ,.\"dltct:d row «h~lon form rTI()I\"e Ihan before. Tl!c MATLA6 com­\nmand r,d{A l produces bases for the R)W space and column space. Bener than \nIhat reducing the combined malrix [A I J prodU« s t~al information about all \nfour of lhe fUOOalllC'nlal subspaces.", "metadata": {"producer": "Adobe Acrobat 9.0 Paper Capture Plug-in", "creator": "PyPDF", "creationdate": "2010-03-03T12:24:37+00:00", "author": "", "moddate": "2010-05-26T00:47:43-03:00", "source": "/home/haas/rag_proj/samples/AAPMOR Website/Introduction to Linear Algebra, 3rd edition (Gilbert Strang) (Z-Library).pdf", "total_pages": 578, "page": 7, "page_label": "8"}}