{"id": "adc3ef9e-86f6-4337-84ab-a4a0b48f7d9b", "text": "that otherwise the\nnull space of the\ncorresponding\nsystem of linear\nequations would be\nnon-trivial, and we\nwould have\ninﬁnitely many\noptimal solutions to\nthe linear regression\nproblem.\npolynomials, we notice that they ﬁt the data better and better. In the ex-\ntreme case of M = N−1 = 9, the function will pass through every single\ndata point. However, these high-degree polynomials oscillate wildly and\nare a poor representation of the underlying function that generated the", "metadata": {"producer": "pdfTeX-1.40.20", "creator": "LaTeX with hyperref", "creationdate": "2019-10-15T12:48:02+01:00", "author": "Marc Peter Deisenroth, A. Aldo Faisal, Cheng Soon Ong", "keywords": "", "moddate": "2020-01-03T10:00:34+02:00", "ptex.fullbanner": "This is pdfTeX, Version 3.14159265-2.6-1.40.20 (TeX Live 2019) kpathsea version 6.3.1", "subject": "", "title": "Mathematics for Machine Learning", "trapped": "/False", "source": "/home/haas/rag_proj/samples/AAPMOR Website/Mathematics for Machine Learning ( etc.) (Z-Library).pdf", "total_pages": 417, "page": 304, "page_label": "299"}}