{"id": "2e889290-5463-497d-8ebe-89988855445b", "text": "context of parameter estimation. Moreover, the propagation of parameter\nuncertainty to the prediction can be valuable in decision-making systems\nfor risk assessment and exploration in the context of data-efﬁcient learn-\ning (Deisenroth et al., 2015; Kamthe and Deisenroth, 2018).\nWhile Bayesian inference is a mathematically principled framework for\nlearning about parameters and making predictions, there are some prac-\ntical challenges that come with it because of the integration problems we", "metadata": {"producer": "pdfTeX-1.40.20", "creator": "LaTeX with hyperref", "creationdate": "2019-10-15T12:48:02+01:00", "author": "Marc Peter Deisenroth, A. Aldo Faisal, Cheng Soon Ong", "keywords": "", "moddate": "2020-01-03T10:00:34+02:00", "ptex.fullbanner": "This is pdfTeX, Version 3.14159265-2.6-1.40.20 (TeX Live 2019) kpathsea version 6.3.1", "subject": "", "title": "Mathematics for Machine Learning", "trapped": "/False", "source": "/home/haas/rag_proj/samples/AAPMOR Website/Mathematics for Machine Learning ( etc.) (Z-Library).pdf", "total_pages": 417, "page": 279, "page_label": "274"}}