{"id": "ab1a3eef-e280-4f23-9b81-4e7f0456b516", "text": "Are you working on a univariate or multivariate time series problem?\nConsidering this question with regard to inputs and outputs may add a further distinction.\nThe number of variables may diﬀer between the inputs and outputs, e.g. the data may not be\nsymmetrical. For example, you may have multiple variables as input to the model and only be\ninterested in predicting one of the variables as output. In this case, there is an assumption in", "metadata": {"producer": "pdfTeX-1.40.18", "creator": "LaTeX with hyperref package", "creationdate": "2018-11-01T07:53:25+11:00", "author": "", "title": "", "subject": "", "keywords": "", "moddate": "2018-11-01T07:53:25+11:00", "trapped": "/False", "ptex.fullbanner": "This is pdfTeX, Version 3.14159265-2.6-1.40.18 (TeX Live 2017) kpathsea version 6.2.3", "source": "/home/haas/rag_proj/samples/AAPMOR Website/Deep Learning for Time Series Forecasting - Predict the Future with MLPs, CNNs and LSTMs in Python (Jason Brownlee) (Z-Library).pdf", "total_pages": 574, "page": 29, "page_label": "13"}}