{"id": "160dba1f-f090-48ae-8f2a-33f89e5f7cb3", "text": "In Ihis ~ase the nullspace af A (and R ) h.u shrunk to the zero vector. n.. solu­\nliOil 10 1I.f = b is ~\"jQ~ (if it exim). There will be m - \" (here 3 - 2) zero rows in \nR . So there are m - n ~ I condition) conditions on b in order to have 0 = 0 in \nthose rows. If />j + bt + In = 0 is satisfied. A.f = b has e~acdy one solution. \nThe Com plete Solution \nTIle OIher e~treme case is full row rank. Now 1I.f = b either has one or infinitely m ay", "metadata": {"producer": "Adobe Acrobat 9.0 Paper Capture Plug-in", "creator": "PyPDF", "creationdate": "2010-03-03T12:24:37+00:00", "author": "", "moddate": "2010-05-26T00:47:43-03:00", "source": "/home/haas/rag_proj/samples/AAPMOR Website/Introduction to Linear Algebra, 3rd edition (Gilbert Strang) (Z-Library).pdf", "total_pages": 578, "page": 155, "page_label": "156"}}