{"id": "e2fc41d4-4b5b-427f-aac2-74d2dc1de315", "text": "(Il the first pivot? \n(1:» the mulliplier III of row I 10 be subtmcted from row 3? \n(c) the IlC'W entry that replaces <Ill after tha( .ublmction'> \n(d) (he second pivot? \n1'robltHls 21_25 inmh\" e p ...... 'rs of A. \n21 C o mpu lC A l. A l. A· and also A p. A lp. A l •• A· p for \n,-[: , \n\"] · ~m \n0 , 0 \n,,'\" - 0 0 o , \n0 0 o 0 \n\" \nFind all the pow ers A l. A l •.. . and AB . (AB) l •.. . f~ \n, ~ [' , '] , ,od B - [' - 0 -n \n2) By lrial and error find real nonzero 2 I:>y 2 malricC's such thaI", "metadata": {"producer": "Adobe Acrobat 9.0 Paper Capture Plug-in", "creator": "PyPDF", "creationdate": "2010-03-03T12:24:37+00:00", "author": "", "moddate": "2010-05-26T00:47:43-03:00", "source": "/home/haas/rag_proj/samples/AAPMOR Website/Introduction to Linear Algebra, 3rd edition (Gilbert Strang) (Z-Library).pdf", "total_pages": 578, "page": 76, "page_label": "77"}}