{"id": "dfbf8365-02a7-4289-86be-e40af6ff5dcf", "text": "Listing 6.6: Example of transforming a univariate time series into a supervised learning problem.\nRunning the example ﬁrst prints the shape of the time series, in this case 10 time steps\nof observations. Next, the series is split into input and output components for a supervised\nlearning problem. We can see that for the chosen representation that we have 7 samples for the\ninput and output and 3 input features. The shape of the output is 7 samples represented as (7,)", "metadata": {"producer": "pdfTeX-1.40.18", "creator": "LaTeX with hyperref package", "creationdate": "2018-11-01T07:53:25+11:00", "author": "", "title": "", "subject": "", "keywords": "", "moddate": "2018-11-01T07:53:25+11:00", "trapped": "/False", "ptex.fullbanner": "This is pdfTeX, Version 3.14159265-2.6-1.40.18 (TeX Live 2017) kpathsea version 6.2.3", "source": "/home/haas/rag_proj/samples/AAPMOR Website/Deep Learning for Time Series Forecasting - Predict the Future with MLPs, CNNs and LSTMs in Python (Jason Brownlee) (Z-Library).pdf", "total_pages": 574, "page": 61, "page_label": "45"}}