{"id": "6676f5ef-0cc9-4cd1-bf8a-9a9ad99e621d", "text": "Consider the term∑N\nn=1(∇Ln(θi)) in (7.15), we can reduce the amount\nof computation by taking a sum over a smaller set of Ln. In contrast to\nbatch gradient descent, which uses all Ln for n= 1,...,N , we randomly\nchoose a subset of Ln for mini-batch gradient descent. In the extreme\ncase, we randomly select only a single Ln to estimate the gradient. The\nkey insight about why taking a subset of data is sensible is to realize that", "metadata": {"producer": "pdfTeX-1.40.20", "creator": "LaTeX with hyperref", "creationdate": "2019-10-15T12:48:02+01:00", "author": "Marc Peter Deisenroth, A. Aldo Faisal, Cheng Soon Ong", "keywords": "", "moddate": "2020-01-03T10:00:34+02:00", "ptex.fullbanner": "This is pdfTeX, Version 3.14159265-2.6-1.40.20 (TeX Live 2019) kpathsea version 6.3.1", "subject": "", "title": "Mathematics for Machine Learning", "trapped": "/False", "source": "/home/haas/rag_proj/samples/AAPMOR Website/Mathematics for Machine Learning ( etc.) (Z-Library).pdf", "total_pages": 417, "page": 237, "page_label": "232"}}