{"id": "27daf27c-d62d-402c-be00-bded2b12dfe2", "text": "(e) When you apply lhe same steps 10 LU. wha t matri~ dQ you get? \n18 If A _ L D U and also A = L 1DIV t with all factors in'·ettible. Illen L = L t and \nD = Dt and V = V t. \"Tlre lac/afl <Ire unique.\" \nDeriv.: the e<juati()ll LitLD .. D 1V tV -1. Are the two ~; des triangular or diag\" \nonal? Ded..ce L = L I and V ... V I (they all ha\"c diagonal 1\"0). \"Then D .. D ,. \n,", "metadata": {"producer": "Adobe Acrobat 9.0 Paper Capture Plug-in", "creator": "PyPDF", "creationdate": "2010-03-03T12:24:37+00:00", "author": "", "moddate": "2010-05-26T00:47:43-03:00", "source": "/home/haas/rag_proj/samples/AAPMOR Website/Introduction to Linear Algebra, 3rd edition (Gilbert Strang) (Z-Library).pdf", "total_pages": 578, "page": 101, "page_label": "102"}}