{"id": "853a76cd-13cf-4a65-9421-b10d0301d2dc", "text": "for multi-step time series forecasting of household power consumption. Speciﬁcally, you learned:\n How to develop and evaluate Univariate and multivariate Encoder-Decoder LSTMs for\nmulti-step time series forecasting.\n How to develop and evaluate an CNN-LSTM Encoder-Decoder model for multi-step time\nseries forecasting.\n How to develop and evaluate a ConvLSTM Encoder-Decoder model for multi-step time\nseries forecasting.\n20.13.1 Next", "metadata": {"producer": "pdfTeX-1.40.18", "creator": "LaTeX with hyperref package", "creationdate": "2018-11-01T07:53:25+11:00", "author": "", "title": "", "subject": "", "keywords": "", "moddate": "2018-11-01T07:53:25+11:00", "trapped": "/False", "ptex.fullbanner": "This is pdfTeX, Version 3.14159265-2.6-1.40.18 (TeX Live 2017) kpathsea version 6.2.3", "source": "/home/haas/rag_proj/samples/AAPMOR Website/Deep Learning for Time Series Forecasting - Predict the Future with MLPs, CNNs and LSTMs in Python (Jason Brownlee) (Z-Library).pdf", "total_pages": 574, "page": 443, "page_label": "427"}}