{"id": "49767533-cba3-4ea6-88f7-03e855bff850", "text": "to which. PageRank computes the weight (importance) xi ⩾0 of a web\nsite ai by counting the number of pages pointing to ai. Moreover, PageR-\nank takes into account the importance of the web sites that link toai. The\nnavigation behavior of a user is then modeled by a transition matrix Aof\nthis graph that tells us with what (click) probability somebody will end up\nc⃝2019 M. P. Deisenroth, A. A. Faisal, C. S. Ong. To be published by Cambridge University Press.", "metadata": {"producer": "pdfTeX-1.40.20", "creator": "LaTeX with hyperref", "creationdate": "2019-10-15T12:48:02+01:00", "author": "Marc Peter Deisenroth, A. Aldo Faisal, Cheng Soon Ong", "keywords": "", "moddate": "2020-01-03T10:00:34+02:00", "ptex.fullbanner": "This is pdfTeX, Version 3.14159265-2.6-1.40.20 (TeX Live 2019) kpathsea version 6.3.1", "subject": "", "title": "Mathematics for Machine Learning", "trapped": "/False", "source": "/home/haas/rag_proj/samples/AAPMOR Website/Mathematics for Machine Learning ( etc.) (Z-Library).pdf", "total_pages": 417, "page": 118, "page_label": "113"}}