{"id": "99937434-090b-47d0-a382-ae9c2918a63c", "text": "directory. We can load this dataset as a Pandas DataFrame using the function read csv().\n# load\nseries = read_csv(' monthly-airline-passengers.csv' , header=0, index_col=0)\nListing 15.1: Load the dataset.\nOnce loaded, we can summarize the shape of the dataset in order to determine the number\nof observations.\n# summarize shape\nprint(series.shape)\nListing 15.2: Summarize the shape of the dataset.\nWe can then create a line plot of the series to get an idea of the structure of the series.\n# plot", "metadata": {"producer": "pdfTeX-1.40.18", "creator": "LaTeX with hyperref package", "creationdate": "2018-11-01T07:53:25+11:00", "author": "", "title": "", "subject": "", "keywords": "", "moddate": "2018-11-01T07:53:25+11:00", "trapped": "/False", "ptex.fullbanner": "This is pdfTeX, Version 3.14159265-2.6-1.40.18 (TeX Live 2017) kpathsea version 6.2.3", "source": "/home/haas/rag_proj/samples/AAPMOR Website/Deep Learning for Time Series Forecasting - Predict the Future with MLPs, CNNs and LSTMs in Python (Jason Brownlee) (Z-Library).pdf", "total_pages": 574, "page": 307, "page_label": "291"}}