{"id": "8ef840cf-c539-4981-94a7-9d8a84181516", "text": "LAB', gilliery. \nSolution To prove ~T A~ > 0 pUI parenthe§cs inlO ~ T LOL T ~ and ~T QA QT~ : \n~TA~ =(LT~)TO(LT ... ) and ~T A~ =(QT~ )T A ( QT~) . \nIf ~ is nonzero. then, = L T ~ and z = QT ~ are nonzero (!hose malrices are in~rtible). \nSo ~ T A~ = :IT D:I = z T A: become s a sum of squares and A is posilive definile: \n~T A ... = ,TO, = <11>\"\\+ ... +<1.)''; > 0 \n~TA~ = :TI\\: = ll:I+···+l.<; > 0 \nH oneSty makes me add one linle commenl 10 Ihis faSl and beauliful proof. A zero in", "metadata": {"producer": "Adobe Acrobat 9.0 Paper Capture Plug-in", "creator": "PyPDF", "creationdate": "2010-03-03T12:24:37+00:00", "author": "", "moddate": "2010-05-26T00:47:43-03:00", "source": "/home/haas/rag_proj/samples/AAPMOR Website/Introduction to Linear Algebra, 3rd edition (Gilbert Strang) (Z-Library).pdf", "total_pages": 578, "page": 346, "page_label": "347"}}