{"id": "c75b6bf5-2ab2-42b7-a95f-6bf77a1424bf", "text": "17 A IlrouP of malm-es indutles AB and A -I if il includes II and 8 . \"Products \nand inverses stay in the group.\" Wh ich of the~ sets are groups? Lowe r trian· \ngular m alrices L wilh !'s on the diagooal. symmetric malrices S. posil;'\" ma­\ntnc..s M . diagonal invenible matrices lJ. pennulation matrices P. matrices with \nQ T;o Q - I. In\\l1:nt IWO more matrix groups. \n, \ni", "metadata": {"producer": "Adobe Acrobat 9.0 Paper Capture Plug-in", "creator": "PyPDF", "creationdate": "2010-03-03T12:24:37+00:00", "author": "", "moddate": "2010-05-26T00:47:43-03:00", "source": "/home/haas/rag_proj/samples/AAPMOR Website/Introduction to Linear Algebra, 3rd edition (Gilbert Strang) (Z-Library).pdf", "total_pages": 578, "page": 116, "page_label": "117"}}