{"id": "fce93913-64aa-4280-ac29-64fe6a40eb98", "text": "[:] .00 \n28 (MATLAB) Take two symmetric matrices with different eigenvectors. say \nA = [g J and B = n n Grnph the eigen\\-'llJues AI (A + rB ) and A1(A + I H ) \nfor - 8 < I < 8. Peter Lv. says on page 113 of Untur AlgtlJru Ihat AI and A1 \nappear to be on a ool1ision course at certain values of r. -Yel al the last minute \nthey tum asi<k.- How ,Iol;e do they oome 'l \n, \nt", "metadata": {"producer": "Adobe Acrobat 9.0 Paper Capture Plug-in", "creator": "PyPDF", "creationdate": "2010-03-03T12:24:37+00:00", "author": "", "moddate": "2010-05-26T00:47:43-03:00", "source": "/home/haas/rag_proj/samples/AAPMOR Website/Introduction to Linear Algebra, 3rd edition (Gilbert Strang) (Z-Library).pdf", "total_pages": 578, "page": 337, "page_label": "338"}}