{"id": "409fe1ee-9461-4ae1-834f-ebc32cfff451", "text": "mulative distribution function FX(x) of a random variable X, and using\nit as the transformation U(x). This leads to the following theorem.\nTheorem 6.15. [Theorem 2.1.10 in Casella and Berger (2002)] Let X be a\ncontinuous random variable with a strictly monotonic cumulative distribu-\ntion function FX(x). Then the random variable Y deﬁned as\nY := FX(x) (6.132)\nhas a uniform distribution.\nDraft (2019-10-15) of “Mathematics for Machine Learning”. Feedback:https://mml-book.com.", "metadata": {"producer": "pdfTeX-1.40.20", "creator": "LaTeX with hyperref", "creationdate": "2019-10-15T12:48:02+01:00", "author": "Marc Peter Deisenroth, A. Aldo Faisal, Cheng Soon Ong", "keywords": "", "moddate": "2020-01-03T10:00:34+02:00", "ptex.fullbanner": "This is pdfTeX, Version 3.14159265-2.6-1.40.20 (TeX Live 2019) kpathsea version 6.3.1", "subject": "", "title": "Mathematics for Machine Learning", "trapped": "/False", "source": "/home/haas/rag_proj/samples/AAPMOR Website/Mathematics for Machine Learning ( etc.) (Z-Library).pdf", "total_pages": 417, "page": 221, "page_label": "216"}}