{"id": "f997b2ef-cfd2-48ec-993b-8c4dde720515", "text": "Take the inner product of those eigenvectors y and t: \n(orthogonal eigenvectors). \nThese eigenvectors ha~e squared length ]2 + I:! + ]2 = 3. After division by ./3 they \nare unit vectors. Th ey were orthogonal. now they are onhO//Ormal. They go into the \ncolumns of the eigem'eclcr matrix S. which diagonalizes A . \nWhen A is real and symmelric, it has real orthogonal eigenvectors. Then 5 is \nQ-an orthogonal matrix. Now A is complex and Hennitian. Its eigenvectors are com­", "metadata": {"producer": "Adobe Acrobat 9.0 Paper Capture Plug-in", "creator": "PyPDF", "creationdate": "2010-03-03T12:24:37+00:00", "author": "", "moddate": "2010-05-26T00:47:43-03:00", "source": "/home/haas/rag_proj/samples/AAPMOR Website/Introduction to Linear Algebra, 3rd edition (Gilbert Strang) (Z-Library).pdf", "total_pages": 578, "page": 497, "page_label": "498"}}