{"id": "319ff410-a808-4cb1-a6a5-6c4f4969c444", "text": "and ﬁle naming conventions. The input data is in CSV format where columns are separated by\nwhitespace. Each of these ﬁles can be loaded as a NumPy array. The load file() function\nbelow loads a dataset given the ﬁle path to the ﬁle and returns the loaded data as a NumPy\narray.\n# load a single file as a numpy array\ndef load_file(filepath):\ndataframe = read_csv(filepath, header=None, delim_whitespace=True)\nreturn dataframe.values\nListing 24.1: Example of a function for loading a single ﬁle.", "metadata": {"producer": "pdfTeX-1.40.18", "creator": "LaTeX with hyperref package", "creationdate": "2018-11-01T07:53:25+11:00", "author": "", "title": "", "subject": "", "keywords": "", "moddate": "2018-11-01T07:53:25+11:00", "trapped": "/False", "ptex.fullbanner": "This is pdfTeX, Version 3.14159265-2.6-1.40.18 (TeX Live 2017) kpathsea version 6.2.3", "source": "/home/haas/rag_proj/samples/AAPMOR Website/Deep Learning for Time Series Forecasting - Predict the Future with MLPs, CNNs and LSTMs in Python (Jason Brownlee) (Z-Library).pdf", "total_pages": 574, "page": 509, "page_label": "493"}}