{"id": "3d63f440-70da-4e63-b8c5-38152175af96", "text": " How the test data must be prepared in order to evaluate the model.\n How to use the model to make predictions with a ﬁnal model in the future.\nA good starting point would be to use the prior seven days. A 1D CNN model expects data\nto have the shape of: [samples, timesteps, features]. One sample will be comprised of\nseven time steps with one feature for the seven days of total daily power consumed. The training", "metadata": {"producer": "pdfTeX-1.40.18", "creator": "LaTeX with hyperref package", "creationdate": "2018-11-01T07:53:25+11:00", "author": "", "title": "", "subject": "", "keywords": "", "moddate": "2018-11-01T07:53:25+11:00", "trapped": "/False", "ptex.fullbanner": "This is pdfTeX, Version 3.14159265-2.6-1.40.18 (TeX Live 2017) kpathsea version 6.2.3", "source": "/home/haas/rag_proj/samples/AAPMOR Website/Deep Learning for Time Series Forecasting - Predict the Future with MLPs, CNNs and LSTMs in Python (Jason Brownlee) (Z-Library).pdf", "total_pages": 574, "page": 387, "page_label": "371"}}