{"id": "402ccf58-9b5a-4a42-a8f6-b038adb5a52a", "text": "of αrestricts the size that the convex hull can take. In other words, the\nbound on α shrinks the convex hull to a smaller volume (Bennett and\nBredensteiner, 2000b). ♦\n12.4 Kernels\nConsider the formulation of the dual SVM (12.41). Notice that the in-\nner product in the objective occurs only between examples xi and xj.\nThere are no inner products between the examples and the parameters.\nTherefore, if we consider a set of features φ(xi) to represent xi, the only", "metadata": {"producer": "pdfTeX-1.40.20", "creator": "LaTeX with hyperref", "creationdate": "2019-10-15T12:48:02+01:00", "author": "Marc Peter Deisenroth, A. Aldo Faisal, Cheng Soon Ong", "keywords": "", "moddate": "2020-01-03T10:00:34+02:00", "ptex.fullbanner": "This is pdfTeX, Version 3.14159265-2.6-1.40.20 (TeX Live 2019) kpathsea version 6.3.1", "subject": "", "title": "Mathematics for Machine Learning", "trapped": "/False", "source": "/home/haas/rag_proj/samples/AAPMOR Website/Mathematics for Machine Learning ( etc.) (Z-Library).pdf", "total_pages": 417, "page": 393, "page_label": "388"}}