{"id": "2bb07c48-d428-4666-872b-4e6a38e950d2", "text": "used for L is 001. required. \n30 E!cplain in words why .«1:) is (c(t) - r)/U(k.t) al lhe end of sI~ ( A. b). \n31 Write a program that muhiplies a N ... ...!iagonal t. limes a Iwo-diagooal U. 000 '1 \nloop from I 10\" when you koow !here are zeros! L limes U should undo ~I u. \n32 I jusl learned MATLAB' s lic-toc command. which mea sures computing lime. \nPreviously I C1)U m <:<l second~ until the answe r appeared. \"'hich required very large", "metadata": {"producer": "Adobe Acrobat 9.0 Paper Capture Plug-in", "creator": "PyPDF", "creationdate": "2010-03-03T12:24:37+00:00", "author": "", "moddate": "2010-05-26T00:47:43-03:00", "source": "/home/haas/rag_proj/samples/AAPMOR Website/Introduction to Linear Algebra, 3rd edition (Gilbert Strang) (Z-Library).pdf", "total_pages": 578, "page": 103, "page_label": "104"}}