{"id": "983ab330-2495-419b-a38a-67a63942590f", "text": "space of dimensions 1, 10, 100, and 500, respectively . We see that even\nwith a single-dimensional principal subspace we get a halfway decent re-\nconstruction of the original digits, which, however, is blurry and generic.\nWith an increasing number of principal components (PCs), the reconstruc-\ntions become sharper and more details are accounted for. With 500 prin-\nDraft (2019-10-15) of “Mathematics for Machine Learning”. Feedback:https://mml-book.com.", "metadata": {"producer": "pdfTeX-1.40.20", "creator": "LaTeX with hyperref", "creationdate": "2019-10-15T12:48:02+01:00", "author": "Marc Peter Deisenroth, A. Aldo Faisal, Cheng Soon Ong", "keywords": "", "moddate": "2020-01-03T10:00:34+02:00", "ptex.fullbanner": "This is pdfTeX, Version 3.14159265-2.6-1.40.20 (TeX Live 2019) kpathsea version 6.3.1", "subject": "", "title": "Mathematics for Machine Learning", "trapped": "/False", "source": "/home/haas/rag_proj/samples/AAPMOR Website/Mathematics for Machine Learning ( etc.) (Z-Library).pdf", "total_pages": 417, "page": 343, "page_label": "338"}}