{"id": "e76463e4-395e-4b1a-863f-eb434174ef03", "text": "serve that µ ∈ (0,1) but θ ∈ R, and therefore the sigmoid function\nsqueezes a real value into the range (0,1). This property is useful in ma-\nchine learning, for example it is used in logistic regression (Bishop, 2006,\nsection 4.3.2), as well as as a nonlinear activation functions in neural net-\nworks (Goodfellow et al., 2016, chapter 6). ♦\nIt is often not obvious how to ﬁnd the parametric form of the conjugate\ndistribution of a particular distribution (for example, those in Table 6.2).", "metadata": {"producer": "pdfTeX-1.40.20", "creator": "LaTeX with hyperref", "creationdate": "2019-10-15T12:48:02+01:00", "author": "Marc Peter Deisenroth, A. Aldo Faisal, Cheng Soon Ong", "keywords": "", "moddate": "2020-01-03T10:00:34+02:00", "ptex.fullbanner": "This is pdfTeX, Version 3.14159265-2.6-1.40.20 (TeX Live 2019) kpathsea version 6.3.1", "subject": "", "title": "Mathematics for Machine Learning", "trapped": "/False", "source": "/home/haas/rag_proj/samples/AAPMOR Website/Mathematics for Machine Learning ( etc.) (Z-Library).pdf", "total_pages": 417, "page": 218, "page_label": "213"}}