{"id": "f19a434d-b4b1-4b95-a641-0da673ed7b1d", "text": "21 \"'l(.<) = I - xl; \"'l(X )\" ~(.<l - x); J \" 4\"\" + 5\"'2 + 6.). \n14 ..,.,. motri. M \",illl thest ni ... cotri .. mu\" be i\",~\"ibk . \n. T(o.) W;II \"'\" be • basi •. W e <\"\"kin·, c\"\"\"\"\" III, .. T(o;). \n3 1 5(7(.)1 .. (-1.2) bIn S(a) .. (- 2. I) and T(S(.)) .. (I. -2). \nC righted matmal", "metadata": {"producer": "Adobe Acrobat 9.0 Paper Capture Plug-in", "creator": "PyPDF", "creationdate": "2010-03-03T12:24:37+00:00", "author": "", "moddate": "2010-05-26T00:47:43-03:00", "source": "/home/haas/rag_proj/samples/AAPMOR Website/Introduction to Linear Algebra, 3rd edition (Gilbert Strang) (Z-Library).pdf", "total_pages": 578, "page": 540, "page_label": "541"}}