{"id": "2b60de01-cc3c-41b2-a7a3-7d2ad8d73bd0", "text": "in<;OI\"1\"«tly gelling uro for the length of (1. I) if ... -e fOfgOl to take lhe: tonjugale. \nNote W e have ~ho!iC n to ~onjugale the firsl vector u. Some authors choose the Sttond \nvector r. T1leir com plex inner product would he uTi. II is a free ~hoice, as long as We \nslick to (H>e or the other. W e wanted to use the single symbol II in the next formula \n100: \nTh~ inntr prot/uti of Au \"\"ilh 0 ~quols Ih~ inna prot/uc/ oj u \",'ilh A\"o : \n\")", "metadata": {"producer": "Adobe Acrobat 9.0 Paper Capture Plug-in", "creator": "PyPDF", "creationdate": "2010-03-03T12:24:37+00:00", "author": "", "moddate": "2010-05-26T00:47:43-03:00", "source": "/home/haas/rag_proj/samples/AAPMOR Website/Introduction to Linear Algebra, 3rd edition (Gilbert Strang) (Z-Library).pdf", "total_pages": 578, "page": 495, "page_label": "496"}}