{"id": "4e6f0469-e69e-43c1-bc61-521add870a09", "text": "nation of all basis vectors, it holds that\nxn =\nD∑\nd=1\nzdnbd\n(10.32)\n=\nD∑\nd=1\n(x⊤\nnbd)bd =\n( D∑\nd=1\nbdb⊤\nd\n)\nxn (10.37a)\n=\n( M∑\nm=1\nbmb⊤\nm\n)\nxn +\n( D∑\nj=M+1\nbjb⊤\nj\n)\nxn, (10.37b)\nwhere we split the sum with D terms into a sum over M and a sum\nover D−M terms. With this result, we ﬁnd that the displacement vector\nxn−˜xn, i.e., the difference vector between the original data point and its\nprojection, is\nxn −˜xn =\n( D∑\nj=M+1\nbjb⊤\nj\n)\nxn (10.38a)\n=\nD∑\nj=M+1\n(x⊤\nnbj)bj . (10.38b)", "metadata": {"producer": "pdfTeX-1.40.20", "creator": "LaTeX with hyperref", "creationdate": "2019-10-15T12:48:02+01:00", "author": "Marc Peter Deisenroth, A. Aldo Faisal, Cheng Soon Ong", "keywords": "", "moddate": "2020-01-03T10:00:34+02:00", "ptex.fullbanner": "This is pdfTeX, Version 3.14159265-2.6-1.40.20 (TeX Live 2019) kpathsea version 6.3.1", "subject": "", "title": "Mathematics for Machine Learning", "trapped": "/False", "source": "/home/haas/rag_proj/samples/AAPMOR Website/Mathematics for Machine Learning ( etc.) (Z-Library).pdf", "total_pages": 417, "page": 335, "page_label": "330"}}