{"id": "a0384506-f1ff-491b-819d-871dff000f31", "text": "2. For any J wilh blocks h B uild M o from bloch IiO Iltat M o' IM o = JT. \n3. For any A = M J M - '. Show Ihal AT is similar 10 IT and SOlO J and 10 A. \n14 F ind tWO more m alrices similar 10 J in Ex ample 3. \n15 Pro,'''' thai deI(A - ).1) = d.et(M -t AM - ).1). (You could wrile I = M -t M aad \n(actor oot d.etM - 1 and detM.) Th is says that A and M -tAM have the same \ncharacteristic polynom ial. So their IUOI S are lhe same eigenvalues.", "metadata": {"producer": "Adobe Acrobat 9.0 Paper Capture Plug-in", "creator": "PyPDF", "creationdate": "2010-03-03T12:24:37+00:00", "author": "", "moddate": "2010-05-26T00:47:43-03:00", "source": "/home/haas/rag_proj/samples/AAPMOR Website/Introduction to Linear Algebra, 3rd edition (Gilbert Strang) (Z-Library).pdf", "total_pages": 578, "page": 358, "page_label": "359"}}