{"id": "60ba5c55-cd56-45f6-b2d7-ef33816af0a3", "text": "7.2 Consider the update equation for stochastic gradient descent (Equation (7.15)).\nWrite down the update when we use a mini-batch size of one.\n7.3 Consider whether the following statements are true or false:\na. The intersection of any two convex sets is convex.\nb. The union of any two convex sets is convex.\nc. The difference of a convex set Afrom another convex set B is convex.\n7.4 Consider whether the following statements are true or false:\na. The sum of any two convex functions is convex.", "metadata": {"producer": "pdfTeX-1.40.20", "creator": "LaTeX with hyperref", "creationdate": "2019-10-15T12:48:02+01:00", "author": "Marc Peter Deisenroth, A. Aldo Faisal, Cheng Soon Ong", "keywords": "", "moddate": "2020-01-03T10:00:34+02:00", "ptex.fullbanner": "This is pdfTeX, Version 3.14159265-2.6-1.40.20 (TeX Live 2019) kpathsea version 6.3.1", "subject": "", "title": "Mathematics for Machine Learning", "trapped": "/False", "source": "/home/haas/rag_proj/samples/AAPMOR Website/Mathematics for Machine Learning ( etc.) (Z-Library).pdf", "total_pages": 417, "page": 252, "page_label": "247"}}